{
  "quiz": {
    "title": "Quiz S01: Shell Fundamentals",
    "description": "Quiz formativ pentru Seminar 01 - Shell Fundamentals",
    "time_limit_minutes": 15,
    "shuffle_questions": true,
    "allowed_attempts": 2
  },
  "questions": [
    {
      "id": "q01",
      "type": "multiple_choice",
      "bloom_level": "remember",
      "learning_outcome": "LO1.1",
      "text": "Ce afișează comanda pwd?",
      "answers": [
        {"text": "Lista de procese", "correct": false, "feedback": "Procesele se afișează cu ps sau top."},
        {"text": "Utilizatorul curent", "correct": false, "feedback": "Utilizatorul curent se afișează cu whoami."},
        {"text": "Directorul curent de lucru", "correct": true, "feedback": "Corect! pwd = Print Working Directory."},
        {"text": "Parola utilizatorului", "correct": false, "feedback": "Parolele nu se afișează în clar în Linux."}
      ]
    },
    {
      "id": "q02",
      "type": "multiple_choice",
      "bloom_level": "remember",
      "learning_outcome": "LO1.2",
      "text": "Care director conține fișierele de configurare ale sistemului?",
      "answers": [
        {"text": "/home", "correct": false, "feedback": "/home conține directoarele utilizatorilor."},
        {"text": "/etc", "correct": true, "feedback": "Corect! /etc conține configurările de sistem."},
        {"text": "/bin", "correct": false, "feedback": "/bin conține executabile de bază."},
        {"text": "/tmp", "correct": false, "feedback": "/tmp este pentru fișiere temporare."}
      ]
    },
    {
      "id": "q03",
      "type": "multiple_choice",
      "bloom_level": "understand",
      "learning_outcome": "LO2.1",
      "text": "Care este diferența dintre shell și terminal?",
      "answers": [
        {"text": "Sunt sinonime", "correct": false, "feedback": "Nu sunt sinonime - au roluri diferite."},
        {"text": "Shell-ul este programul care interpretează comenzi, terminalul este interfața", "correct": true, "feedback": "Corect! Shell-ul (bash) interpretează, terminalul este interfața grafică."},
        {"text": "Terminalul interpretează comenzi, shell-ul este fereastra", "correct": false, "feedback": "Este invers - shell-ul interpretează comenzile."},
        {"text": "Nu există diferență funcțională", "correct": false, "feedback": "Există diferențe clare de funcționalitate."}
      ]
    },
    {
      "id": "q04",
      "type": "multiple_choice",
      "bloom_level": "understand",
      "learning_outcome": "LO2.2",
      "text": "Ce tip de cale este '/home/stud/proiect'?",
      "answers": [
        {"text": "Cale relativă", "correct": false, "feedback": "Căile relative nu încep cu /."},
        {"text": "Cale absolută", "correct": true, "feedback": "Corect! Începe cu / (rădăcina), deci e absolută."},
        {"text": "Cale simbolică", "correct": false, "feedback": "Căile simbolice sunt link-uri, nu un tip de cale."},
        {"text": "Cale virtuală", "correct": false, "feedback": "Nu există conceptul de cale virtuală în Linux."}
      ]
    },
    {
      "id": "q05",
      "type": "multiple_choice",
      "bloom_level": "understand",
      "learning_outcome": "LO3.1",
      "text": "Dacă setez VAR='test' fără export și pornesc un subshell, ce va afișa echo $VAR în subshell?",
      "answers": [
        {"text": "test", "correct": false, "feedback": "Variabilele locale nu sunt vizibile în subprocese."},
        {"text": "Nimic (string gol)", "correct": true, "feedback": "Corect! Fără export, variabila nu e în environment."},
        {"text": "Eroare", "correct": false, "feedback": "Nu e eroare, doar rezultat gol."},
        {"text": "$VAR literal", "correct": false, "feedback": "Fără ghilimele simple, $VAR se expandează."}
      ]
    },
    {
      "id": "q06",
      "type": "multiple_choice",
      "bloom_level": "apply",
      "learning_outcome": "LO4.1",
      "text": "Ce comandă creează structura de directoare /proiect/src/main/java dacă nu există?",
      "answers": [
        {"text": "mkdir /proiect/src/main/java", "correct": false, "feedback": "Fără -p, mkdir eșuează dacă părinții nu există."},
        {"text": "mkdir -p /proiect/src/main/java", "correct": true, "feedback": "Corect! -p (parents) creează toate directoarele necesare."},
        {"text": "mkdir -r /proiect/src/main/java", "correct": false, "feedback": "-r nu este o opțiune validă pentru mkdir."},
        {"text": "mkdir --create /proiect/src/main/java", "correct": false, "feedback": "--create nu este o opțiune validă pentru mkdir."}
      ]
    },
    {
      "id": "q07",
      "type": "multiple_choice",
      "bloom_level": "apply",
      "learning_outcome": "LO4.2",
      "text": "Tocmai ai modificat ~/.bashrc. Ce comandă aplică modificările în sesiunea curentă?",
      "answers": [
        {"text": "restart bash", "correct": false, "feedback": "restart nu este o comandă validă în acest context."},
        {"text": "source ~/.bashrc", "correct": true, "feedback": "Corect! source (sau .) execută scriptul în shell-ul curent."},
        {"text": "refresh ~/.bashrc", "correct": false, "feedback": "refresh nu este o comandă Bash."},
        {"text": "reload ~/.bashrc", "correct": false, "feedback": "reload nu este o comandă Bash standard."}
      ]
    },
    {
      "id": "q08",
      "type": "multiple_choice",
      "bloom_level": "apply",
      "learning_outcome": "LO5.1",
      "text": "Ce fișiere creează comanda: touch file{1,2,3}.txt ?",
      "answers": [
        {"text": "file{1,2,3}.txt (un singur fișier)", "correct": false, "feedback": "Brace expansion expandează înainte de execuție."},
        {"text": "file1.txt, file2.txt, file3.txt", "correct": true, "feedback": "Corect! Brace expansion creează 3 fișiere separate."},
        {"text": "file123.txt", "correct": false, "feedback": "Nu concatenează - creează fișiere separate."},
        {"text": "Eroare de sintaxă", "correct": false, "feedback": "Sintaxa este validă - e brace expansion."}
      ]
    },
    {
      "id": "q09",
      "type": "multiple_choice",
      "bloom_level": "analyse",
      "learning_outcome": "LO6.1",
      "text": "NUME='Ion'; echo 'Salut $NUME' afișează:",
      "answers": [
        {"text": "Salut Ion", "correct": false, "feedback": "Single quotes nu expandează variabile."},
        {"text": "Salut $NUME", "correct": true, "feedback": "Corect! Single quotes păstrează totul literal."},
        {"text": "Eroare de sintaxă", "correct": false, "feedback": "Sintaxa este corectă."},
        {"text": "Salut (gol)", "correct": false, "feedback": "$NUME rămâne literal în single quotes."}
      ]
    },
    {
      "id": "q10",
      "type": "multiple_choice",
      "bloom_level": "analyse",
      "learning_outcome": "LO6.2",
      "text": "Ce semnifică exit code 0 în Linux?",
      "answers": [
        {"text": "Eroare", "correct": false, "feedback": "Non-zero înseamnă eroare."},
        {"text": "Comandă inexistentă", "correct": false, "feedback": "127 înseamnă comandă inexistentă."},
        {"text": "Succes", "correct": true, "feedback": "Corect! 0 = succes în convenția Unix."},
        {"text": "Permisiuni insuficiente", "correct": false, "feedback": "1 sau alt cod non-zero pentru erori de permisiuni."}
      ]
    }
  ],
  "metadata": {
    "version": "1.0",
    "seminar": 1,
    "bloom_distribution": {
      "remember": "20%",
      "understand": "30%",
      "apply": "30%",
      "analyse": "20%"
    }
  }
}
